asyncpg_listen/__init__.py
asyncpg_listen/listener.py
asyncpg_listen/py.typed
asyncpg_listen-0.0.9.dist-info/LICENSE
asyncpg_listen-0.0.9.dist-info/METADATA
asyncpg_listen-0.0.9.dist-info/WHEEL
asyncpg_listen-0.0.9.dist-info/top_level.txt
asyncpg_listen-0.0.9.dist-info/RECORD
