Metadata-Version: 2.1
Name: asyncpg-listen
Version: 0.0.9
Summary: Helps to use PostgreSQL listen/notify with asyncpg
Home-page: https://github.com/Pliner/asyncpg-listen
Author: Yury Pliner
Author-email: yury.pliner@gmail.com
License: MIT
Platform: macOS
Platform: POSIX
Platform: Windows
Classifier: License :: OSI Approved :: MIT License
Classifier: Intended Audience :: Developers
Classifier: Programming Language :: Python :: 3
Classifier: Programming Language :: Python :: 3 :: Only
Classifier: Programming Language :: Python :: 3.11
Classifier: Programming Language :: Python :: 3.12
Classifier: Programming Language :: Python :: 3.13
Classifier: Operating System :: OS Independent
Classifier: Environment :: Web Environment
Classifier: Development Status :: 5 - Production/Stable
Classifier: Framework :: AsyncIO
Classifier: Typing :: Typed
Requires-Python: >=3.11
License-File: LICENSE
Requires-Dist: asyncpg>=0.27.0
